[
  {
    "model": "perma.folder",
    "pk": 22,
    "fields": {
      "name": "Empty root folder",
      "parent": null,
      "creation_timestamp": "2014-09-02T16:57:03Z",
      "created_by": 1,
      "owned_by": 1,
      "organization": null,
      "is_shared_folder": false,
      "is_root_folder": true,
      "lft": 1,
      "rght": 2,
      "tree_id": 1,
      "level": 0
    }
  },
  {
    "model": "perma.folder",
    "pk": 23,
    "fields": {
      "name": "Personal Links",
      "parent": null,
      "creation_timestamp": "2014-09-02T16:57:03Z",
      "created_by": 2,
      "owned_by": 2,
      "organization": null,
      "is_shared_folder": false,
      "is_root_folder": true,
      "lft": 1,
      "rght": 4,
      "tree_id": 2,
      "level": 0
    }
  },
  {
    "model": "perma.folder",
    "pk": 24,
    "fields": {
      "name": "Personal Links",
      "parent": null,
      "creation_timestamp": "2014-09-02T16:57:03Z",
      "created_by": 3,
      "owned_by": 3,
      "organization": null,
      "is_shared_folder": false,
      "is_root_folder": true,
      "lft": 1,
      "rght": 2,
      "tree_id": 3,
      "level": 0
    }
  },
  {
    "model": "perma.folder",
    "pk": 25,
    "fields": {
      "name": "Personal Links",
      "parent": null,
      "creation_timestamp": "2014-09-02T16:57:03Z",
      "created_by": 4,
      "owned_by": 4,
      "organization": null,
      "is_shared_folder": false,
      "is_root_folder": true,
      "lft": 1,
      "rght": 2,
      "tree_id": 4,
      "level": 0
    }
  },
  {
    "model": "perma.folder",
    "pk": 26,
    "fields": {
      "name": "Personal Links",
      "parent": null,
      "creation_timestamp": "2014-09-02T16:57:03Z",
      "created_by": 5,
      "owned_by": 5,
      "organization": null,
      "is_shared_folder": false,
      "is_root_folder": true,
      "lft": 1,
      "rght": 2,
      "tree_id": 5,
      "level": 0
    }
  },
  {
    "model": "perma.folder",
    "pk": 27,
    "fields": {
      "name": "Test Journal",
      "parent": null,
      "creation_timestamp": "2014-09-02T16:58:10Z",
      "created_by": null,
      "owned_by": null,
      "organization": 1,
      "is_shared_folder": true,
      "is_root_folder": false,
      "lft": 1,
      "rght": 6,
      "tree_id": 10,
      "level": 0
    }
  },
  {
    "model": "perma.folder",
    "pk": 28,
    "fields": {
      "name": "Another Journal",
      "parent": null,
      "creation_timestamp": "2014-09-02T16:58:10Z",
      "created_by": null,
      "owned_by": null,
      "organization": 2,
      "is_shared_folder": true,
      "is_root_folder": false,
      "lft": 1,
      "rght": 6,
      "tree_id": 11,
      "level": 0
    }
  },
  {
    "model": "perma.folder",
    "pk": 29,
    "fields": {
      "name": "Empty child folder",
      "parent": 25,
      "creation_timestamp": "2014-09-02T16:57:03Z",
      "created_by": 4,
      "owned_by": 4,
      "organization": null,
      "is_shared_folder": false,
      "is_root_folder": false,
      "lft": 1,
      "rght": 2,
      "tree_id": 4,
      "level": 1
    }
  },
  {
    "model": "perma.folder",
    "pk": 30,
    "fields": {
      "name": "Non-empty child folder",
      "parent": 25,
      "creation_timestamp": "2014-09-02T16:57:03Z",
      "created_by": 4,
      "owned_by": 4,
      "organization": null,
      "is_shared_folder": false,
      "is_root_folder": false,
      "lft": 1,
      "rght": 2,
      "tree_id": 4,
      "level": 1
    }
  },
  {
    "model": "perma.folder",
    "pk": 31,
    "fields": {
      "name": "A Third Journal",
      "parent": null,
      "creation_timestamp": "2014-09-02T16:58:10Z",
      "created_by": null,
      "owned_by": null,
      "organization": 3,
      "is_shared_folder": true,
      "is_root_folder": false,
      "lft": 1,
      "rght": 6,
      "tree_id": 12,
      "level": 0
    }
  },
  {
    "model": "perma.folder",
    "pk": 32,
    "fields": {
      "name": "Personal Links",
      "parent": null,
      "creation_timestamp": "2014-09-02T16:57:03Z",
      "created_by": 6,
      "owned_by": 6,
      "organization": null,
      "is_shared_folder": false,
      "is_root_folder": true,
      "lft": 1,
      "rght": 2,
      "tree_id": 13,
      "level": 0
    }
  },
  {
    "model": "perma.folder",
    "pk": 33,
    "fields": {
      "name": "Personal Links",
      "parent": null,
      "creation_timestamp": "2014-09-02T16:57:03Z",
      "created_by": 6,
      "owned_by": 6,
      "organization": null,
      "is_shared_folder": false,
      "is_root_folder": true,
      "lft": 1,
      "rght": 2,
      "tree_id": 14,
      "level": 0
    }
  },
  {
    "model": "perma.folder",
    "pk": 34,
    "fields": {
      "name": "Test Journal subfolder1",
      "parent": 27,
      "creation_timestamp": "2015-01-28T21:43:38Z",
      "created_by": null,
      "owned_by": null,
      "organization": 1,
      "is_shared_folder": false,
      "is_root_folder": false,
      "lft": 2,
      "rght": 3,
      "tree_id": 10,
      "level": 1
    }
  },
  {
    "model": "perma.folder",
    "pk": 35,
    "fields": {
      "name": "Test Journal subfolder2",
      "parent": 27,
      "creation_timestamp": "2015-01-28T21:43:45Z",
      "created_by": null,
      "owned_by": null,
      "organization": 1,
      "is_shared_folder": false,
      "is_root_folder": false,
      "lft": 4,
      "rght": 5,
      "tree_id": 10,
      "level": 1
    }
  },
  {
    "model": "perma.folder",
    "pk": 36,
    "fields": {
      "name": "Another Journal subfolder2",
      "parent": 28,
      "creation_timestamp": "2015-01-28T21:44:34Z",
      "created_by": null,
      "owned_by": null,
      "organization": 2,
      "is_shared_folder": false,
      "is_root_folder": false,
      "lft": 4,
      "rght": 5,
      "tree_id": 11,
      "level": 1
    }
  },
  {
    "model": "perma.folder",
    "pk": 37,
    "fields": {
      "name": "Another Journal subfolder1",
      "parent": 28,
      "creation_timestamp": "2015-01-28T21:44:43Z",
      "created_by": null,
      "owned_by": null,
      "organization": 2,
      "is_shared_folder": false,
      "is_root_folder": false,
      "lft": 2,
      "rght": 3,
      "tree_id": 11,
      "level": 1
    }
  },
  {
    "model": "perma.folder",
    "pk": 38,
    "fields": {
      "name": "A Third Journal subfolder1",
      "parent": 31,
      "creation_timestamp": "2015-01-28T21:44:53Z",
      "created_by": null,
      "owned_by": null,
      "organization": 3,
      "is_shared_folder": false,
      "is_root_folder": false,
      "lft": 2,
      "rght": 3,
      "tree_id": 12,
      "level": 1
    }
  },
  {
    "model": "perma.folder",
    "pk": 39,
    "fields": {
      "name": "A Third Journal subfolder2",
      "parent": 31,
      "creation_timestamp": "2015-01-28T21:45:00Z",
      "created_by": null,
      "owned_by": null,
      "organization": 3,
      "is_shared_folder": false,
      "is_root_folder": false,
      "lft": 4,
      "rght": 5,
      "tree_id": 12,
      "level": 1
    }
  },
  {
    "model": "perma.folder",
    "pk": 40,
    "fields": {
      "name": "Another Library's Journal",
      "parent": null,
      "creation_timestamp": "2014-09-02T16:58:10Z",
      "created_by": null,
      "owned_by": null,
      "organization": 4,
      "is_shared_folder": true,
      "is_root_folder": false,
      "lft": 1,
      "rght": 6,
      "tree_id": 15,
      "level": 0
    }
  },
  {
    "model": "perma.folder",
    "pk": 41,
    "fields": {
      "name": "Personal Links",
      "parent": null,
      "creation_timestamp": "2014-09-02T16:57:03Z",
      "created_by": 6,
      "owned_by": 7,
      "organization": null,
      "is_shared_folder": false,
      "is_root_folder": true,
      "lft": 1,
      "rght": 2,
      "tree_id": 16,
      "level": 0
    }
  },
  {
    "model": "perma.folder",
    "pk": 42,
    "fields": {
      "name": "Personal Links",
      "parent": null,
      "creation_timestamp": "2014-09-02T16:57:03Z",
      "created_by": 9,
      "owned_by": 9,
      "organization": null,
      "is_shared_folder": false,
      "is_root_folder": true,
      "lft": 1,
      "rght": 2,
      "tree_id": 17,
      "level": 0
    }
  },
  {
    "model": "perma.folder",
    "pk": 43,
    "fields": {
      "name": "Personal Links",
      "parent": null,
      "creation_timestamp": "2016-10-18T16:57:03Z",
      "created_by": 9,
      "owned_by": 9,
      "organization": null,
      "is_shared_folder": false,
      "is_root_folder": true,
      "lft": 1,
      "rght": 2,
      "tree_id": 18,
      "level": 0
    }
  },
  {
    "model": "perma.folder",
    "pk": 44,
    "fields": {
      "name": "Personal Links",
      "parent": null,
      "creation_timestamp": "2016-10-17T16:57:03Z",
      "created_by": 9,
      "owned_by": 9,
      "organization": null,
      "is_shared_folder": false,
      "is_root_folder": true,
      "lft": 1,
      "rght": 2,
      "tree_id": 19,
      "level": 0
    }
  },
  {
    "model": "perma.folder",
    "pk": 45,
    "fields": {
      "name": "Personal Links",
      "parent": null,
      "creation_timestamp": "2016-10-18T16:57:03Z",
      "created_by": 9,
      "owned_by": 9,
      "organization": null,
      "is_shared_folder": false,
      "is_root_folder": true,
      "lft": 1,
      "rght": 2,
      "tree_id": 20,
      "level": 0
    }
  },
  {
    "model": "perma.folder",
    "pk": 46,
    "fields": {
      "name": "Personal Links",
      "parent": null,
      "creation_timestamp": "2016-10-18T16:57:03Z",
      "created_by": 9,
      "owned_by": 9,
      "organization": null,
      "is_shared_folder": false,
      "is_root_folder": true,
      "lft": 1,
      "rght": 2,
      "tree_id": 21,
      "level": 0
    }
  },
  {
    "model": "perma.folder",
    "pk": 47,
    "fields": {
      "name": "Personal Links",
      "parent": null,
      "creation_timestamp": "2016-10-18T16:57:03Z",
      "created_by": 9,
      "owned_by": 9,
      "organization": null,
      "is_shared_folder": false,
      "is_root_folder": true,
      "lft": 1,
      "rght": 2,
      "tree_id": 22,
      "level": 0
    }
  },
  {
    "model": "perma.folder",
    "pk": 48,
    "fields": {
      "name": "Personal Links",
      "parent": null,
      "creation_timestamp": "2016-10-18T16:57:03Z",
      "created_by": 9,
      "owned_by": 9,
      "organization": null,
      "is_shared_folder": false,
      "is_root_folder": true,
      "lft": 1,
      "rght": 2,
      "tree_id": 23,
      "level": 0
    }
  },
  {
    "model": "perma.folder",
    "pk": 49,
    "fields": {
      "name": "Personal Links",
      "parent": null,
      "creation_timestamp": "2016-10-18T16:57:03Z",
      "created_by": 9,
      "owned_by": 9,
      "organization": null,
      "is_shared_folder": false,
      "is_root_folder": true,
      "lft": 1,
      "rght": 2,
      "tree_id": 24,
      "level": 0
    }
  },
  {
    "model": "perma.folder",
    "pk": 50,
    "fields": {
      "name": "Personal Links",
      "parent": null,
      "creation_timestamp": "2017-09-28T19:33:47Z",
      "created_by": 17,
      "owned_by": 17,
      "organization": null,
      "is_shared_folder": false,
      "is_root_folder": true,
      "lft": 1,
      "rght": 2,
      "tree_id": 25,
      "level": 0
    }
  },
  {
    "model": "perma.folder",
    "pk": 51,
    "fields": {
      "name": "Some Case",
      "parent": null,
      "creation_timestamp": "2017-09-28T19:34:40Z",
      "created_by": null,
      "owned_by": null,
      "organization": 5,
      "is_shared_folder": true,
      "is_root_folder": false,
      "lft": 1,
      "rght": 2,
      "tree_id": 26,
      "level": 0
    }
  },
  {
    "model": "perma.folder",
    "pk": 52,
    "fields": {
      "name": "Some Other Case",
      "parent": null,
      "creation_timestamp": "2017-09-28T19:34:53Z",
      "created_by": null,
      "owned_by": null,
      "organization": 6,
      "is_shared_folder": true,
      "is_root_folder": false,
      "lft": 1,
      "rght": 2,
      "tree_id": 27,
      "level": 0
    }
  },
  {
    "model": "perma.folder",
    "pk": 53,
    "fields": {
      "name": "Personal Links",
      "parent": null,
      "creation_timestamp": "2017-09-28T19:36:07Z",
      "created_by": 18,
      "owned_by": 18,
      "organization": null,
      "is_shared_folder": false,
      "is_root_folder": true,
      "lft": 1,
      "rght": 2,
      "tree_id": 28,
      "level": 0
    }
  },
  {
    "model": "perma.folder",
    "pk": 54,
    "fields": {
      "name": "Personal Links",
      "parent": null,
      "creation_timestamp": "2017-09-28T19:36:07Z",
      "created_by": 19,
      "owned_by": 19,
      "organization": null,
      "is_shared_folder": false,
      "is_root_folder": true,
      "lft": 1,
      "rght": 2,
      "tree_id": 29,
      "level": 0
    }
  },
  {
    "model": "perma.folder",
    "pk": 55,
    "fields": {
      "name": "Personal Links",
      "parent": null,
      "creation_timestamp": "2017-09-28T19:36:07Z",
      "created_by": 20,
      "owned_by": 20,
      "organization": null,
      "is_shared_folder": false,
      "is_root_folder": true,
      "lft": 1,
      "rght": 2,
      "tree_id": 30,
      "level": 0
    }
  },
  {
    "model": "perma.folder",
    "pk": 56,
    "fields": {
      "name": "Personal Links",
      "parent": null,
      "creation_timestamp": "2017-09-28T19:36:07Z",
      "created_by": 21,
      "owned_by": 21,
      "organization": null,
      "is_shared_folder": false,
      "is_root_folder": true,
      "lft": 1,
      "rght": 2,
      "tree_id": 31,
      "level": 0
    }
  },
  {
    "model": "perma.folder",
    "pk": 57,
    "fields": {
      "name": "Personal Links",
      "parent": null,
      "creation_timestamp": "2017-09-28T19:36:07Z",
      "created_by": 22,
      "owned_by": 22,
      "organization": null,
      "is_shared_folder": false,
      "is_root_folder": true,
      "lft": 1,
      "rght": 2,
      "tree_id": 32,
      "level": 0
    }
  },
  {
    "model": "perma.folder",
    "pk": 58,
    "fields": {
      "name": "Personal Links",
      "parent": null,
      "creation_timestamp": "2017-09-28T19:36:07Z",
      "created_by": 21,
      "owned_by": 21,
      "organization": null,
      "is_shared_folder": false,
      "is_root_folder": true,
      "lft": 1,
      "rght": 2,
      "tree_id": 33,
      "level": 0
    }
  },
  {
    "model": "perma.folder",
    "pk": 59,
    "fields": {
      "name": "Sponsored Links",
      "parent": null,
      "creation_timestamp": "2017-09-28T19:36:07Z",
      "created_by": 20,
      "owned_by": 20,
      "organization": null,
      "is_shared_folder": false,
      "is_root_folder": false,
      "is_sponsored_root_folder": true,
      "lft": 1,
      "rght": 10,
      "tree_id": 49,
      "level": 0
    }
  },
  {
    "model": "perma.folder",
    "pk": 60,
    "fields": {
      "name": "Test Library",
      "parent": null,
      "creation_timestamp": "2017-09-28T19:36:07Z",
      "created_by": 20,
      "owned_by": 20,
      "sponsored_by": 1,
      "organization": null,
      "is_shared_folder": false,
      "is_root_folder": false,
      "is_sponsored_root_folder": false,
      "lft": 4,
      "rght": 9,
      "parent": 59,
      "tree_id": 49,
      "level": 1
    }
  },
  {
    "model": "perma.folder",
    "pk": 61,
    "fields": {
      "name": "Sponsored Subfolder",
      "parent": null,
      "creation_timestamp": "2017-09-28T19:36:07Z",
      "created_by": 20,
      "owned_by": 20,
      "sponsored_by": 1,
      "organization": null,
      "is_shared_folder": false,
      "is_root_folder": false,
      "is_sponsored_root_folder": false,
      "lft": 5,
      "rght": 8,
      "parent": 60,
      "tree_id": 49,
      "level": 2
    }
  },
  {
    "model": "perma.folder",
    "pk": 62,
    "fields": {
      "name": "Sponsored Links",
      "parent": null,
      "creation_timestamp": "2017-09-28T19:36:07Z",
      "created_by": 22,
      "owned_by": 22,
      "organization": null,
      "is_shared_folder": false,
      "is_root_folder": false,
      "is_sponsored_root_folder": true,
      "lft": 1,
      "rght": 6,
      "tree_id": 50,
      "level": 0
    }
  },
  {
    "model": "perma.folder",
    "pk": 63,
    "fields": {
      "name": "Test Library",
      "parent": null,
      "creation_timestamp": "2017-09-28T19:36:07Z",
      "created_by": 22,
      "owned_by": 22,
      "sponsored_by": 1,
      "organization": null,
      "is_shared_folder": false,
      "is_root_folder": false,
      "is_sponsored_root_folder": false,
      "lft": 2,
      "rght": 5,
      "parent": 62,
      "tree_id": 50,
      "level": 1,
      "read_only": true
    }
  },
  {
    "model": "perma.folder",
    "pk": 64,
    "fields": {
      "name": "Sponsored Subsubfolder",
      "parent": null,
      "creation_timestamp": "2017-09-28T19:36:07Z",
      "created_by": 20,
      "owned_by": 20,
      "sponsored_by": 1,
      "organization": null,
      "is_shared_folder": false,
      "is_root_folder": false,
      "is_sponsored_root_folder": false,
      "lft": 6,
      "rght": 7,
      "parent": 61,
      "tree_id": 49,
      "level": 3
    }
  },
  {
    "model": "perma.folder",
    "pk": 65,
    "fields": {
      "name": "Inactive Sponsored Subfolder",
      "parent": null,
      "creation_timestamp": "2017-09-28T19:36:07Z",
      "created_by": 22,
      "owned_by": 22,
      "sponsored_by": 1,
      "organization": null,
      "is_shared_folder": false,
      "is_root_folder": false,
      "is_sponsored_root_folder": false,
      "lft": 3,
      "rght": 4,
      "parent": 63,
      "tree_id": 50,
      "level": 2,
      "read_only": true
    }
  },
  {
    "model": "perma.folder",
    "pk": 66,
    "fields": {
      "name": "Personal Links",
      "parent": null,
      "creation_timestamp": "2002-02-28T00:00:00Z",
      "created_by": 24,
      "owned_by": 24,
      "organization": null,
      "is_shared_folder": false,
      "is_root_folder": true,
      "lft": 1,
      "rght": 2,
      "tree_id": 51,
      "level": 0
    }
  }
]
